CHANGELOG.md
README.md
RELEASE.md
autohooks/plugins/autopep8/__init__.py
autohooks/plugins/autopep8/autopep8.py
autohooks_plugin_autopep8-0.0.4.dist-info/LICENSE
autohooks_plugin_autopep8-0.0.4.dist-info/WHEEL
autohooks_plugin_autopep8-0.0.4.dist-info/METADATA
autohooks_plugin_autopep8-0.0.4.dist-info/RECORD
